jptest2/JPSetup.py
jptest2/JPTest.py
jptest2/JPTestComparison.py
jptest2/JPTestGet.py
jptest2/RunTest.py
jptest2/__init__.py
jptest2/__main__.py
jptest2/notebook/Notebook.py
jptest2/notebook/NotebookCell.py
jptest2/notebook/NotebookError.py
jptest2/notebook/NotebookFunctionCall.py
jptest2/notebook/NotebookFunctionReplacement.py
jptest2/notebook/NotebookFunctionWrapper.py
jptest2/notebook/NotebookReference.py
jptest2/notebook/__init__.py
jptest2/notebook/util.py
jptest2/notebook/kernels/DuckDBNotebook.py
jptest2/notebook/kernels/PythonNotebook.py
jptest2/notebook/kernels/SQLiteNotebook.py
jptest2/notebook/kernels/__init__.py
jptest2/tests/__init__.py
jptest2/tests/test_code_execution.py
jptest2/tests/test_function_execution.py
jptest2/tests/test_function_replacement.py
jptest2/tests/test_function_tracking.py
jptest2/tests/test_notebook_reference.py
jptest2/tests/test_ref_and_get.py
jptest2-2.2.1.dist-info/LICENSE
jptest2-2.2.1.dist-info/METADATA
jptest2-2.2.1.dist-info/WHEEL
jptest2-2.2.1.dist-info/top_level.txt
jptest2-2.2.1.dist-info/RECORD
