Metadata-Version: 2.2
Name: jptest2
Version: 2.2.1
Summary: write graded unit tests for Jupyter Notebooks in a few lines of code
Home-page: https://github.com/erictroebs/jptest
Author: Eric Tröbs
Author-email: eric.troebs@tu-ilmenau.de
Project-URL: Bug Tracker, https://github.com/erictroebs/jptest/issues
Classifier: Programming Language :: Python :: 3
Classifier: License :: OSI Approved :: MIT License
Classifier: Operating System :: OS Independent
Requires-Python: >=3.9
License-File: LICENSE
Requires-Dist: jupyter
Requires-Dist: aiofiles==24.1.0
Provides-Extra: sqlite
Requires-Dist: aiosqlite==0.21.0; extra == "sqlite"
Provides-Extra: demo
Requires-Dist: watchfiles==1.0.4; extra == "demo"
Dynamic: author
Dynamic: author-email
Dynamic: classifier
Dynamic: description
Dynamic: description-content-type
Dynamic: home-page
Dynamic: project-url
Dynamic: provides-extra
Dynamic: requires-dist
Dynamic: requires-python
Dynamic: summary
